streamsx/standard/__init__.py
streamsx/standard/_adapter.py
streamsx/standard/_version.py
streamsx/standard/files.py
streamsx/standard/relational.py
streamsx/standard/utility.py
streamsx/standard/tests/data.csv
streamsx.standard-1.5.0.dist-info/DESCRIPTION.rst
streamsx.standard-1.5.0.dist-info/LICENSE.txt
streamsx.standard-1.5.0.dist-info/METADATA
streamsx.standard-1.5.0.dist-info/RECORD
streamsx.standard-1.5.0.dist-info/WHEEL
streamsx.standard-1.5.0.dist-info/metadata.json
streamsx.standard-1.5.0.dist-info/top_level.txt
