Metadata-Version: 2.0
Name: streamsx.standard
Version: 1.5.0
Summary: Standard toolkit integration for IBM Streams
Home-page: https://github.com/IBMStreams/pypi.streamsx.standard
Author: IBM Streams @ github.com
Author-email: hegermar@de.ibm.com
License: Apache License - Version 2.0
Keywords: streams,ibmstreams,streaming,analytics,streaming-analytics
Platform: UNKNOWN
Classifier: Development Status :: 5 - Production/Stable
Classifier: License :: OSI Approved :: Apache Software License
Classifier: Programming Language :: Python :: 3
Classifier: Programming Language :: Python :: 3.6
Classifier: Programming Language :: Python :: 3.7
Requires-Dist: streamsx (>=1.14.6)
